apyrs/__init__.py
apyrs/extension.py
apyrs-0.2.dev0.dist-info/METADATA
apyrs-0.2.dev0.dist-info/WHEEL
apyrs-0.2.dev0.dist-info/top_level.txt
apyrs-0.2.dev0.dist-info/RECORD
